{
	"configurations" : 
	[
		{
			"directories" : 
			[
				{
					"build" : ".",
					"jsonFile" : "directory-.-Debug-d0094a50bb2071803777.json",
					"minimumCMakeVersion" : 
					{
						"string" : "3.28"
					},
					"projectIndex" : 0,
					"source" : ".",
					"targetIndexes" : 
					[
						0,
						1,
						2,
						3,
						4,
						5,
						6,
						7,
						8,
						9,
						10,
						11,
						12,
						13,
						14,
						15,
						16,
						17,
						18,
						19,
						20,
						21,
						22,
						23,
						24,
						25,
						26
					]
				}
			],
			"name" : "Debug",
			"projects" : 
			[
				{
					"directoryIndexes" : 
					[
						0
					],
					"name" : "CProjects",
					"targetIndexes" : 
					[
						0,
						1,
						2,
						3,
						4,
						5,
						6,
						7,
						8,
						9,
						10,
						11,
						12,
						13,
						14,
						15,
						16,
						17,
						18,
						19,
						20,
						21,
						22,
						23,
						24,
						25,
						26
					]
				}
			],
			"targets" : 
			[
				{
					"directoryIndex" : 0,
					"id" : "1toN::@6890427a1f51a3e7e1df",
					"jsonFile" : "target-1toN-Debug-40804dad0e99dfeb9dc1.json",
					"name" : "1toN",
					"projectIndex" : 0
				},
				{
					"directoryIndex" : 0,
					"id" : "AsciiPrint::@6890427a1f51a3e7e1df",
					"jsonFile" : "target-AsciiPrint-Debug-17b4999195ba704d75b3.json",
					"name" : "AsciiPrint",
					"projectIndex" : 0
				},
				{
					"directoryIndex" : 0,
					"id" : "Automobile::@6890427a1f51a3e7e1df",
					"jsonFile" : "target-Automobile-Debug-6549f30b987c718b0f1f.json",
					"name" : "Automobile",
					"projectIndex" : 0
				},
				{
					"directoryIndex" : 0,
					"id" : "BinarySearch::@6890427a1f51a3e7e1df",
					"jsonFile" : "target-BinarySearch-Debug-999c4abd704da96e1549.json",
					"name" : "BinarySearch",
					"projectIndex" : 0
				},
				{
					"directoryIndex" : 0,
					"id" : "Break::@6890427a1f51a3e7e1df",
					"jsonFile" : "target-Break-Debug-e0f44dfeff253e4da764.json",
					"name" : "Break",
					"projectIndex" : 0
				},
				{
					"directoryIndex" : 0,
					"id" : "BubbleSort::@6890427a1f51a3e7e1df",
					"jsonFile" : "target-BubbleSort-Debug-021552e83f28c8a7c73e.json",
					"name" : "BubbleSort",
					"projectIndex" : 0
				},
				{
					"directoryIndex" : 0,
					"id" : "CheckNumber::@6890427a1f51a3e7e1df",
					"jsonFile" : "target-CheckNumber-Debug-c7dc95dc8a383d606bd5.json",
					"name" : "CheckNumber",
					"projectIndex" : 0
				},
				{
					"directoryIndex" : 0,
					"id" : "CountZero::@6890427a1f51a3e7e1df",
					"jsonFile" : "target-CountZero-Debug-9f9defa6b01b4ae9d1ba.json",
					"name" : "CountZero",
					"projectIndex" : 0
				},
				{
					"directoryIndex" : 0,
					"id" : "ExponentialSearch::@6890427a1f51a3e7e1df",
					"jsonFile" : "target-ExponentialSearch-Debug-e93bd4c431fc9e22dbcf.json",
					"name" : "ExponentialSearch",
					"projectIndex" : 0
				},
				{
					"directoryIndex" : 0,
					"id" : "Factorial::@6890427a1f51a3e7e1df",
					"jsonFile" : "target-Factorial-Debug-2c7f3618be79224e0dc8.json",
					"name" : "Factorial",
					"projectIndex" : 0
				},
				{
					"directoryIndex" : 0,
					"id" : "FibonacciSearch::@6890427a1f51a3e7e1df",
					"jsonFile" : "target-FibonacciSearch-Debug-3507d31a7eafd02168a6.json",
					"name" : "FibonacciSearch",
					"projectIndex" : 0
				},
				{
					"directoryIndex" : 0,
					"id" : "HarryAndDigits::@6890427a1f51a3e7e1df",
					"jsonFile" : "target-HarryAndDigits-Debug-7618f3c5403c1c42da23.json",
					"name" : "HarryAndDigits",
					"projectIndex" : 0
				},
				{
					"directoryIndex" : 0,
					"id" : "HashAndStar::@6890427a1f51a3e7e1df",
					"jsonFile" : "target-HashAndStar-Debug-fe3e4ec94f8cfc71ea51.json",
					"name" : "HashAndStar",
					"projectIndex" : 0
				},
				{
					"directoryIndex" : 0,
					"id" : "InterpolationSearch::@6890427a1f51a3e7e1df",
					"jsonFile" : "target-InterpolationSearch-Debug-607ee400d9ade0e18398.json",
					"name" : "InterpolationSearch",
					"projectIndex" : 0
				},
				{
					"directoryIndex" : 0,
					"id" : "JumpSearch::@6890427a1f51a3e7e1df",
					"jsonFile" : "target-JumpSearch-Debug-61e5251c2da2b0ff9b9d.json",
					"name" : "JumpSearch",
					"projectIndex" : 0
				},
				{
					"directoryIndex" : 0,
					"id" : "LinearSearch::@6890427a1f51a3e7e1df",
					"jsonFile" : "target-LinearSearch-Debug-7155a5ed499e849492ba.json",
					"name" : "LinearSearch",
					"projectIndex" : 0
				},
				{
					"directoryIndex" : 0,
					"id" : "Main::@6890427a1f51a3e7e1df",
					"jsonFile" : "target-Main-Debug-8ea1406020cdbdf2e310.json",
					"name" : "Main",
					"projectIndex" : 0
				},
				{
					"directoryIndex" : 0,
					"id" : "Nto1::@6890427a1f51a3e7e1df",
					"jsonFile" : "target-Nto1-Debug-4b5f437f79de54dd1ccf.json",
					"name" : "Nto1",
					"projectIndex" : 0
				},
				{
					"directoryIndex" : 0,
					"id" : "Palindrome::@6890427a1f51a3e7e1df",
					"jsonFile" : "target-Palindrome-Debug-7f83bd400e0dee70bf8c.json",
					"name" : "Palindrome",
					"projectIndex" : 0
				},
				{
					"directoryIndex" : 0,
					"id" : "PrintAlpha::@6890427a1f51a3e7e1df",
					"jsonFile" : "target-PrintAlpha-Debug-bc44873ca983168a2fac.json",
					"name" : "PrintAlpha",
					"projectIndex" : 0
				},
				{
					"directoryIndex" : 0,
					"id" : "ProductOfDigits::@6890427a1f51a3e7e1df",
					"jsonFile" : "target-ProductOfDigits-Debug-72fa3deed361a72c24b0.json",
					"name" : "ProductOfDigits",
					"projectIndex" : 0
				},
				{
					"directoryIndex" : 0,
					"id" : "ReverseNumber::@6890427a1f51a3e7e1df",
					"jsonFile" : "target-ReverseNumber-Debug-dfeb93375680975f7c14.json",
					"name" : "ReverseNumber",
					"projectIndex" : 0
				},
				{
					"directoryIndex" : 0,
					"id" : "SortedOrNot::@6890427a1f51a3e7e1df",
					"jsonFile" : "target-SortedOrNot-Debug-eeb89437595ead186b2a.json",
					"name" : "SortedOrNot",
					"projectIndex" : 0
				},
				{
					"directoryIndex" : 0,
					"id" : "SumOfDigits::@6890427a1f51a3e7e1df",
					"jsonFile" : "target-SumOfDigits-Debug-2c0085653f31347ad4e6.json",
					"name" : "SumOfDigits",
					"projectIndex" : 0
				},
				{
					"directoryIndex" : 0,
					"id" : "SumOfN::@6890427a1f51a3e7e1df",
					"jsonFile" : "target-SumOfN-Debug-5e3589f4186f4e2729b3.json",
					"name" : "SumOfN",
					"projectIndex" : 0
				},
				{
					"directoryIndex" : 0,
					"id" : "Swap::@6890427a1f51a3e7e1df",
					"jsonFile" : "target-Swap-Debug-791154dc64da9dbb9c20.json",
					"name" : "Swap",
					"projectIndex" : 0
				},
				{
					"directoryIndex" : 0,
					"id" : "SwitchCase::@6890427a1f51a3e7e1df",
					"jsonFile" : "target-SwitchCase-Debug-307a7f985bb273638d82.json",
					"name" : "SwitchCase",
					"projectIndex" : 0
				}
			]
		}
	],
	"kind" : "codemodel",
	"paths" : 
	{
		"build" : "C:/Users/prana/CLionProjects/CProjects/cmake-build-debug",
		"source" : "C:/Users/prana/CLionProjects/CProjects"
	},
	"version" : 
	{
		"major" : 2,
		"minor" : 6
	}
}
